Workbook

Sheet Start Here
B1: PR. Final Project - "Data Intelligence Dashboard"
B2: Built on your Final Project Dataset: 250 transactions, 50 customers, 10 products, 5 regions
B4: Required topic | C4: Where | D4: Status
B5: Date & Time: TODAY, NOW, DATEDIF, EOMONTH | C5: Analysis section 1, Raw Data O:P,R | D5: Done
B6: FILTER function | C6: Analysis section 2 | D6: Done (helper version + 365 formula)
B7: Conditional formatting with icons/arrows | C7: Analysis (MoM %), Dashboard | D7: Done
B8: Timestamp with NOW + iterative calc | C8: Analysis section 3 | D8: Done (iterative ON)
B9: What-if: Scenario Manager, Goal Seek | C9: Analysis section 4 | D9: Model ready - run the tools (Manual Steps)
B10: Linear regression (Toolpak) | C10: Analysis section 5 | D10: Formulas done - Toolpak run by hand
B11: Data analysis & storytelling | C11: Insights Report | D11: Done (live text)
B12: GroupBy / High-value customers | C12: Analysis section 6 | D12: Done
B13: Dashboard: pivots, pivot charts, slicers, timeline | C13: Dashboard + Manual Steps | D13: Interactive dropdown dashboard done; pivots/slicers by hand
B14: KPI indicators with conditional formatting | C14: Dashboard rows 7-13 | D14: Done
B15: Most purchased product / repeating names | C15: Analysis section 7 | D15: Done
... B18: Final report | C18: Insights Report | D18: Done
B20: Colour legend
B21: Yellow cell + blue text = input you can change
B22: Black text = formula (do not overwrite)
B23: Sheets: Raw Data > Analysis > Visualizations > Dashboard > Insights Report > Manual Steps
B24: Note: data runs 11-Apr-2024 to 11-Apr-2025, so Apr-2024 and Apr-2025 are partial months and are left out of the trend and KPIs.

Sheet Raw Data
A1: Transaction_ID | B1: Date | C1: Customer_ID | D1: Customer_Name | E1: Product_ID | F1: Product_Name | G1: Category | H1: Quantity | I1: Unit_Price | J1: Payment_Method | K1: Region | L1: Customer_Segment | M1: Customer_Since | N1: Total_Amount | O1: Month End | P1: Order Age (Months) | Q1: Filter Helper | R1: Tenure at Order (Months)
A2: TRX0155 | B2: 45393 | C2: CUST023 | D2: Paul Baker | E2: P009 | F2: Monitor | G2: Electronics | H2: 3 | I2: 249.99 | J2: Cash | K2: Central | L2: Basic | M2: 44425 | N2: 749.97 | O2: =EOMONTH(B2,0) -> 45412 | P2: =DATEDIF(B2,TODAY(),"m") -> 30 | Q2: =IF(K2=Analysis!$B$16,COUNTIF($K$2:K2,Analysis!$B$16),"") -> 1 | R2: =IFERROR(DATEDIF(M2,B2,"m"),"") -> 31
A3: TRX0023 | B3: 45396 | C3: CUST013 | D3: Joseph Jackson | E3: P009 | F3: Monitor | G3: Electronics | H3: 3 | I3: 249.99 | J3: Credit Card | K3: Central | L3: Premium | M3: 44575 | N3: 749.97 | O3: =EOMONTH(B3,0) -> 45412 | P3: =DATEDIF(B3,TODAY(),"m") -> 29 | Q3: =IF(K3=Analysis!$B$16,COUNTIF($K$2:K3,Analysis!$B$16),"") -> 2 | R3: =IFERROR(DATEDIF(M3,B3,"m"),"") -> 27
A4: TRX0139 | B4: 45399 | C4: CUST021 | D4: Kevin Scott | E4: P005 | F4: Blender | G4: Appliances | H4: 3 | I4: 59.99 | J4: PayPal | K4: South | L4: Standard | M4: 45262 | N4: 179.97 | O4: =EOMONTH(B4,0) -> 45412 | P4: =DATEDIF(B4,TODAY(),"m") -> 29 | Q4: =IF(K4=Analysis!$B$16,COUNTIF($K$2:K4,Analysis!$B$16),"") | R4: =IFERROR(DATEDIF(M4,B4,"m"),"") -> 4
A5: TRX0043 | B5: 45400 | C5: CUST046 | D5: Kathleen Bennett | E5: P005 | F5: Blender | G5: Appliances | H5: 3 | I5: 59.99 | J5: Cash | K5: North | L5: Premium | M5: 45114 | N5: 179.97 | O5: =EOMONTH(B5,0) -> 45412 | P5: =DATEDIF(B5,TODAY(),"m") -> 29 | Q5: =IF(K5=Analysis!$B$16,COUNTIF($K$2:K5,Analysis!$B$16),"") | R5: =IFERROR(DATEDIF(M5,B5,"m"),"") -> 9
A6: TRX0212 | B6: 45400 | C6: CUST003 | D6: Michael Brown | E6: P008 | F6: Bookshelf | G6: Furniture | H6: 5 | I6: 149.99 | J6: Credit Card | K6: North | L6: Premium | M6: 45295 | N6: 749.95 | O6: =EOMONTH(B6,0) -> 45412 | P6: =DATEDIF(B6,TODAY(),"m") -> 29 | Q6: =IF(K6=Analysis!$B$16,COUNTIF($K$2:K6,Analysis!$B$16),"") | R6: =IFERROR(DATEDIF(M6,B6,"m"),"") -> 3
A7: TRX0092 | B7: 45403 | C7: CUST024 | D7: Dorothy Nelson | E7: P005 | F7: Blender | G7: Appliances | H7: 2 | I7: 59.99 | J7: Cash | K7: West | L7: Standard | M7: 44746 | N7: 119.98 | O7: =EOMONTH(B7,0) -> 45412 | P7: =DATEDIF(B7,TODAY(),"m") -> 29 | Q7: =IF(K7=Analysis!$B$16,COUNTIF($K$2:K7,Analysis!$B$16),"") | R7: =IFERROR(DATEDIF(M7,B7,"m"),"") -> 21
A8: TRX0193 | B8: 45403 | C8: CUST024 | D8: Dorothy Nelson | E8: P003 | F8: Headphones | G8: Electronics | H8: 5 | I8: 149.99 | J8: Credit Card | K8: Central | L8: Standard | M8: 44418 | N8: 749.95 | O8: =EOMONTH(B8,0) -> 45412 | P8: =DATEDIF(B8,TODAY(),"m") -> 29 | Q8: =IF(K8=Analysis!$B$16,COUNTIF($K$2:K8,Analysis!$B$16),"") -> 3 | R8: =IFERROR(DATEDIF(M8,B8,"m"),"") -> 32
A9: TRX0240 | B9: 45403 | C9: CUST017 | D9: Charles Allen | E9: P005 | F9: Blender | G9: Appliances | H9: 3 | I9: 59.99 | J9: Debit Card | K9: South | L9: Basic | M9: 45007 | N9: 179.97 | O9: =EOMONTH(B9,0) -> 45412 | P9: =DATEDIF(B9,TODAY(),"m") -> 29 | Q9: =IF(K9=Analysis!$B$16,COUNTIF($K$2:K9,Analysis!$B$16),"") | R9: =IFERROR(DATEDIF(M9,B9,"m"),"") -> 12
A10: TRX0135 | B10: 45405 | C10: CUST009 | D10: Robert Thomas | E10: P001 | F10: Laptop | G10: Electronics | H10: 3 | I10: 899.99 | J10: PayPal | K10: East | L10: Standard | M10: 45299 | N10: 2699.97 | O10: =EOMONTH(B10,0) -> 45412 | P10: =DATEDIF(B10,TODAY(),"m") -> 29 | Q10: =IF(K10=Analysis!$B$16,COUNTIF($K$2:K10,Analysis!$B$16),"") | R10: =IFERROR(DATEDIF(M10,B10,"m"),"") -> 3
A11: TRX0138 | B11: 45408 | C11: CUST022 | D11: Susan Green | E11: P008 | F11: Bookshelf | G11: Furniture | H11: 1 | I11: 149.99 | J11: Credit Card | K11: West | L11: Standard | M11: 45103 | N11: 149.99 | O11: =EOMONTH(B11,0) -> 45412 | P11: =DATEDIF(B11,TODAY(),"m") -> 29 | Q11: =IF(K11=Analysis!$B$16,COUNTIF($K$2:K11,Analysis!$B$16),"") | R11: =IFERROR(DATEDIF(M11,B11,"m"),"") -> 10
A12: TRX0185 | B12: 45408 | C12: CUST026 | D12: Karen Hill | E12: P005 | F12: Blender | G12: Appliances | H12: 3 | I12: 59.99 | J12: Cash | K12: West | L12: Premium | M12: 45207 | N12: 179.97 | O12: =EOMONTH(B12,0) -> 45412 | P12: =DATEDIF(B12,TODAY(),"m") -> 29 | Q12: =IF(K12=Analysis!$B$16,COUNTIF($K$2:K12,Analysis!$B$16),"") | R12: =IFERROR(DATEDIF(M12,B12,"m"),"") -> 6
A13: TRX0209 | B13: 45408 | C13: CUST046 | D13: Kathleen Bennett | E13: P008 | F13: Bookshelf | G13: Furniture | H13: 5 | I13: 149.99 | J13: Debit Card | K13: North | L13: Basic | M13: 44830 | N13: 749.95 | O13: =EOMONTH(B13,0) -> 45412 | P13: =DATEDIF(B13,TODAY(),"m") -> 29 | Q13: =IF(K13=Analysis!$B$16,COUNTIF($K$2:K13,Analysis!$B$16),"") | R13: =IFERROR(DATEDIF(M13,B13,"m"),"") -> 19
... A251: TRX0120 | B251: 45758 | C251: CUST045 | D251: Douglas Watson | E251: P002 | F251: Smartphone | G251: Electronics | H251: 3 | I251: 699.99 | J251: PayPal | K251: North | L251: Basic | M251: 44909 | N251: 2099.97 | O251: =EOMONTH(B251,0) -> 45777 | P251: =DATEDIF(B251,TODAY(),"m") -> 18 | Q251: =IF(K251=Analysis!$B$16,COUNTIF($K$2:K251,Analysis!$B$16),"") | R251: =IFERROR(DATEDIF(M251,B251,"m"),"") -> 27

Sheet Analysis
A1: ANALYSIS - every number is a formula (yellow cells with blue text are inputs you can change)
A3: 1. DATE & TIME FUNCTIONS (TODAY, NOW, DATEDIF, EOMONTH)
A4: Today's date [TODAY] | B4: =TODAY() -> 46307
A5: Current date & time [NOW] | B5: =NOW() -> 46307.275
A6: First order date | B6: =MIN('Raw Data'!$B$2:$B$251) -> 45393
A7: Latest order date | B7: =MAX('Raw Data'!$B$2:$B$251) -> 45758
A8: Days since last order | B8: =TODAY()-B7 -> 549
A9: Data span [DATEDIF] | B9: =DATEDIF(B6,B7,"y")&" yr "&DATEDIF(B6,B7,"ym")&" months "&DATEDIF(B6,B7,"md")&" days" -> 1 yr 0 months 0 days
A10: Month-end of latest order [EOMONTH] | B10: =EOMONTH(B7,0) -> 45777
A11: Days left in that month | B11: =B10-B7 -> 19
A12: First day of next month | B12: =EOMONTH(B7,0)+1 -> 45778
A13: Months from first order till today | B13: =DATEDIF(B6,TODAY(),"m") -> 30
A15: 2. FILTER FUNCTION - multi-value return (pick a region)
A16: Select Region | B16: Central
A17: Excel 365 FILTER formula to type: | B17: =FILTER('Raw Data'!A2:N251,'Raw Data'!K2:K251=B16,"No data")
A18: Matching orders | B18: =COUNTIF('Raw Data'!$K$2:$K$251,B16) -> 54
A20: # | B20: Transaction | C20: Date | D20: Customer | E20: Product | F20: Total Amount
A21: 1 | B21: =IFERROR(INDEX('Raw Data'!$A$2:$A$251,MATCH($A21,'Raw Data'!$Q$2:$Q$251,0)),"") -> TRX0155 | C21: =IFERROR(INDEX('Raw Data'!$B$2:$B$251,MATCH($A21,'Raw Data'!$Q$2:$Q$251,0)),"") -> 45393 | D21: =IFERROR(INDEX('Raw Data'!$D$2:$D$251,MATCH($A21,'Raw Data'!$Q$2:$Q$251,0)),"") -> Paul Baker | E21: =IFERROR(INDEX('Raw Data'!$F$2:$F$251,MATCH($A21,'Raw Data'!$Q$2:$Q$251,0)),"") -> Monitor | F21: =IFERROR(INDEX('Raw Data'!$N$2:$N$251,MATCH($A21,'Raw Data'!$Q$2:$Q$251,0)),"") -> 749.97
A22: 2 | B22: =IFERROR(INDEX('Raw Data'!$A$2:$A$251,MATCH($A22,'Raw Data'!$Q$2:$Q$251,0)),"") -> TRX0023 | C22: =IFERROR(INDEX('Raw Data'!$B$2:$B$251,MATCH($A22,'Raw Data'!$Q$2:$Q$251,0)),"") -> 45396 | D22: =IFERROR(INDEX('Raw Data'!$D$2:$D$251,MATCH($A22,'Raw Data'!$Q$2:$Q$251,0)),"") -> Joseph Jackson | E22: =IFERROR(INDEX('Raw Data'!$F$2:$F$251,MATCH($A22,'Raw Data'!$Q$2:$Q$251,0)),"") -> Monitor | F22: =IFERROR(INDEX('Raw Data'!$N$2:$N$251,MATCH($A22,'Raw Data'!$Q$2:$Q$251,0)),"") -> 749.97
A23: 3 | B23: =IFERROR(INDEX('Raw Data'!$A$2:$A$251,MATCH($A23,'Raw Data'!$Q$2:$Q$251,0)),"") -> TRX0193 | C23: =IFERROR(INDEX('Raw Data'!$B$2:$B$251,MATCH($A23,'Raw Data'!$Q$2:$Q$251,0)),"") -> 45403 | D23: =IFERROR(INDEX('Raw Data'!$D$2:$D$251,MATCH($A23,'Raw Data'!$Q$2:$Q$251,0)),"") -> Dorothy Nelson | E23: =IFERROR(INDEX('Raw Data'!$F$2:$F$251,MATCH($A23,'Raw Data'!$Q$2:$Q$251,0)),"") -> Headphones | F23: =IFERROR(INDEX('Raw Data'!$N$2:$N$251,MATCH($A23,'Raw Data'!$Q$2:$Q$251,0)),"") -> 749.95
A24: 4 | B24: =IFERROR(INDEX('Raw Data'!$A$2:$A$251,MATCH($A24,'Raw Data'!$Q$2:$Q$251,0)),"") -> TRX0063 | C24: =IFERROR(INDEX('Raw Data'!$B$2:$B$251,MATCH($A24,'Raw Data'!$Q$2:$Q$251,0)),"") -> 45425 | D24: =IFERROR(INDEX('Raw Data'!$D$2:$D$251,MATCH($A24,'Raw Data'!$Q$2:$Q$251,0)),"") -> Helen Roberts | E24: =IFERROR(INDEX('Raw Data'!$F$2:$F$251,MATCH($A24,'Raw Data'!$Q$2:$Q$251,0)),"") -> Blender | F24: =IFERROR(INDEX('Raw Data'!$N$2:$N$251,MATCH($A24,'Raw Data'!$Q$2:$Q$251,0)),"") -> 119.98
A25: 5 | B25: =IFERROR(INDEX('Raw Data'!$A$2:$A$251,MATCH($A25,'Raw Data'!$Q$2:$Q$251,0)),"") -> TRX0202 | C25: =IFERROR(INDEX('Raw Data'!$B$2:$B$251,MATCH($A25,'Raw Data'!$Q$2:$Q$251,0)),"") -> 45441 | D25: =IFERROR(INDEX('Raw Data'!$D$2:$D$251,MATCH($A25,'Raw Data'!$Q$2:$Q$251,0)),"") -> Harry Morgan | E25: =IFERROR(INDEX('Raw Data'!$F$2:$F$251,MATCH($A25,'Raw Data'!$Q$2:$Q$251,0)),"") -> Keyboard | F25: =IFERROR(INDEX('Raw Data'!$N$2:$N$251,MATCH($A25,'Raw Data'!$Q$2:$Q$251,0)),"") -> 269.97
A26: 6 | B26: =IFERROR(INDEX('Raw Data'!$A$2:$A$251,MATCH($A26,'Raw Data'!$Q$2:$Q$251,0)),"") -> TRX0088 | C26: =IFERROR(INDEX('Raw Data'!$B$2:$B$251,MATCH($A26,'Raw Data'!$Q$2:$Q$251,0)),"") -> 45456 | D26: =IFERROR(INDEX('Raw Data'!$D$2:$D$251,MATCH($A26,'Raw Data'!$Q$2:$Q$251,0)),"") -> Lisa Anderson | E26: =IFERROR(INDEX('Raw Data'!$F$2:$F$251,MATCH($A26,'Raw Data'!$Q$2:$Q$251,0)),"") -> Keyboard | F26: =IFERROR(INDEX('Raw Data'!$N$2:$N$251,MATCH($A26,'Raw Data'!$Q$2:$Q$251,0)),"") -> 449.95
A27: 7 | B27: =IFERROR(INDEX('Raw Data'!$A$2:$A$251,MATCH($A27,'Raw Data'!$Q$2:$Q$251,0)),"") -> TRX0078 | C27: =IFERROR(INDEX('Raw Data'!$B$2:$B$251,MATCH($A27,'Raw Data'!$Q$2:$Q$251,0)),"") -> 45469 | D27: =IFERROR(INDEX('Raw Data'!$D$2:$D$251,MATCH($A27,'Raw Data'!$Q$2:$Q$251,0)),"") -> Kevin Scott | E27: =IFERROR(INDEX('Raw Data'!$F$2:$F$251,MATCH($A27,'Raw Data'!$Q$2:$Q$251,0)),"") -> Coffee Maker | F27: =IFERROR(INDEX('Raw Data'!$N$2:$N$251,MATCH($A27,'Raw Data'!$Q$2:$Q$251,0)),"") -> 79.99
A28: 8 | B28: =IFERROR(INDEX('Raw Data'!$A$2:$A$251,MATCH($A28,'Raw Data'!$Q$2:$Q$251,0)),"") -> TRX0096 | C28: =IFERROR(INDEX('Raw Data'!$B$2:$B$251,MATCH($A28,'Raw Data'!$Q$2:$Q$251,0)),"") -> 45474 | D28: =IFERROR(INDEX('Raw Data'!$D$2:$D$251,MATCH($A28,'Raw Data'!$Q$2:$Q$251,0)),"") -> Emma Wilson | E28: =IFERROR(INDEX('Raw Data'!$F$2:$F$251,MATCH($A28,'Raw Data'!$Q$2:$Q$251,0)),"") -> Keyboard | F28: =IFERROR(INDEX('Raw Data'!$N$2:$N$251,MATCH($A28,'Raw Data'!$Q$2:$Q$251,0)),"") -> 179.98
A29: 9 | B29: =IFERROR(INDEX('Raw Data'!$A$2:$A$251,MATCH($A29,'Raw Data'!$Q$2:$Q$251,0)),"") -> TRX0070 | C29: =IFERROR(INDEX('Raw Data'!$B$2:$B$251,MATCH($A29,'Raw Data'!$Q$2:$Q$251,0)),"") -> 45476 | D29: =IFERROR(INDEX('Raw Data'!$D$2:$D$251,MATCH($A29,'Raw Data'!$Q$2:$Q$251,0)),"") -> David Martinez | E29: =IFERROR(INDEX('Raw Data'!$F$2:$F$251,MATCH($A29,'Raw Data'!$Q$2:$Q$251,0)),"") -> Coffee Maker | F29: =IFERROR(INDEX('Raw Data'!$N$2:$N$251,MATCH($A29,'Raw Data'!$Q$2:$Q$251,0)),"") -> 399.95
A30: 10 | B30: =IFERROR(INDEX('Raw Data'!$A$2:$A$251,MATCH($A30,'Raw Data'!$Q$2:$Q$251,0)),"") -> TRX0018 | C30: =IFERROR(INDEX('Raw Data'!$B$2:$B$251,MATCH($A30,'Raw Data'!$Q$2:$Q$251,0)),"") -> 45484 | D30: =IFERROR(INDEX('Raw Data'!$D$2:$D$251,MATCH($A30,'Raw Data'!$Q$2:$Q$251,0)),"") -> Joseph Jackson | E30: =IFERROR(INDEX('Raw Data'!$F$2:$F$251,MATCH($A30,'Raw Data'!$Q$2:$Q$251,0)),"") -> Headphones | F30: =IFERROR(INDEX('Raw Data'!$N$2:$N$251,MATCH($A30,'Raw Data'!$Q$2:$Q$251,0)),"") -> 149.99
A31: Shows the first 10 matches using a helper column (works in every Excel version). In Excel 365 the FILTER formula above returns all matches in one cell.
A33: 3. TIMESTAMP using NOW() + iterative calculation
A34: Type anything here ->
A35: Timestamp (freezes once typed) | B35: =IF(B34="","",IF(B35="",NOW(),B35))
A36: Needs File > Options > Formulas > Enable iterative calculation (already ON in this file).
A38: 4. WHAT-IF ANALYSIS (Scenario Manager + Goal Seek)
A39: Base revenue (actual) | B39: =SUM('Raw Data'!$N$2:$N$251) -> 229192.47
A40: Price change % | B40: 0.05
A41: Quantity change % | B41: 0.1
A42: Discount % | B42: 0.02
A43: Projected revenue | B43: =B39*(1+B40)*(1+B41)*(1-B42) -> 259422.96
A44: Change vs base | B44: =B43-B39 -> 30230.487
A45: Goal Seek target revenue | B45: 290000 | C45: My assumption: 25% above actual revenue - change it
A46: Gap to target | B46: =B43-B45 -> -30577.043
A47: Monthly revenue target (dashboard KPI) | B47: 20000 | C47: My assumption: about 10% above the average full month - change it
A49: Scenario | B49: Price % | C49: Quantity % | D49: Discount % | E49: Projected Revenue
A50: Best case | B50: 0.1 | C50: 0.15 | D50: 0 | E50: =$B$39*(1+B50)*(1+C50)*(1-D50) -> 289928.47
A51: Base case | B51: 0.05 | C51: 0.1 | D51: 0.02 | E51: =$B$39*(1+B51)*(1+C51)*(1-D51) -> 259422.96
A52: Worst case | B52: 0 | C52: -0.05 | D52: 0.05 | E52: =$B$39*(1+B52)*(1+C52)*(1-D52) -> 206846.2
A54: 5. LINEAR REGRESSION - monthly revenue trend (full months only)
A55: Month # | B55: Month Start | C55: Label | D55: Revenue | E55: Trend (fitted) | F55: MoM % | H55: Statistic | I55: Value
A56: 1 | B56: 45413 | C56: =TEXT(B56,"mmm-yy") -> May-24 | D56: =SUMIFS('Raw Data'!$N$2:$N$251,'Raw Data'!$B$2:$B$251,">="&B56,'Raw Data'!$B$2:$B$251,"<="&EOMONTH(B56,0)) -> 17039.35 | E56: =$I$57+$I$56*A56 -> 16607.629 | H56: Slope ($ per month) | I56: =SLOPE(D56:D66,A56:A66) -> 338.35264
A57: 2 | B57: 45444 | C57: =TEXT(B57,"mmm-yy") -> Jun-24 | D57: =SUMIFS('Raw Data'!$N$2:$N$251,'Raw Data'!$B$2:$B$251,">="&B57,'Raw Data'!$B$2:$B$251,"<="&EOMONTH(B57,0)) -> 19299.45 | E57: =$I$57+$I$56*A57 -> 16945.981 | F57: =D57/D56-1 -> 0.13264004 | H57: Intercept | I57: =INTERCEPT(D56:D66,A56:A66) -> 16269.276
A58: 3 | B58: 45474 | C58: =TEXT(B58,"mmm-yy") -> Jul-24 | D58: =SUMIFS('Raw Data'!$N$2:$N$251,'Raw Data'!$B$2:$B$251,">="&B58,'Raw Data'!$B$2:$B$251,"<="&EOMONTH(B58,0)) -> 18479.4 | E58: =$I$57+$I$56*A58 -> 17284.334 | F58: =D58/D57-1 -> -0.042490848 | H58: R-squared | I58: =RSQ(D56:D66,A56:A66) -> 0.076447365
A59: 4 | B59: 45505 | C59: =TEXT(B59,"mmm-yy") -> Aug-24 | D59: =SUMIFS('Raw Data'!$N$2:$N$251,'Raw Data'!$B$2:$B$251,">="&B59,'Raw Data'!$B$2:$B$251,"<="&EOMONTH(B59,0)) -> 15759.43 | E59: =$I$57+$I$56*A59 -> 17622.687 | F59: =D59/D58-1 -> -0.1471893 | H59: Correlation | I59: =CORREL(A56:A66,D56:D66) -> 0.27649117
A60: 5 | B60: 45536 | C60: =TEXT(B60,"mmm-yy") -> Sep-24 | D60: =SUMIFS('Raw Data'!$N$2:$N$251,'Raw Data'!$B$2:$B$251,">="&B60,'Raw Data'!$B$2:$B$251,"<="&EOMONTH(B60,0)) -> 12989.51 | E60: =$I$57+$I$56*A60 -> 17961.039 | F60: =D60/D59-1 -> -0.1757627 | H60: Forecast month 12 | I60: =FORECAST(12,D56:D66,A56:A66) -> 20329.508
A61: 6 | B61: 45566 | C61: =TEXT(B61,"mmm-yy") -> Oct-24 | D61: =SUMIFS('Raw Data'!$N$2:$N$251,'Raw Data'!$B$2:$B$251,">="&B61,'Raw Data'!$B$2:$B$251,"<="&EOMONTH(B61,0)) -> 20609.52 | E61: =$I$57+$I$56*A61 -> 18299.392 | F61: =D61/D60-1 -> 0.58662798 | H61: =IF(I56>0,"Revenue is trending UP by about $"&TEXT(I56,"#,##0")&" every month","Revenue is trending DOWN by about $"&TEXT(-I56,"#,##0")&" every month") -> Revenue is trending UP by about $338 every month
A62: 7 | B62: 45597 | C62: =TEXT(B62,"mmm-yy") -> Nov-24 | D62: =SUMIFS('Raw Data'!$N$2:$N$251,'Raw Data'!$B$2:$B$251,">="&B62,'Raw Data'!$B$2:$B$251,"<="&EOMONTH(B62,0)) -> 12309.44 | E62: =$I$57+$I$56*A62 -> 18637.744 | F62: =D62/D61-1 -> -0.40273039
A63: 8 | B63: 45627 | C63: =TEXT(B63,"mmm-yy") -> Dec-24 | D63: =SUMIFS('Raw Data'!$N$2:$N$251,'Raw Data'!$B$2:$B$251,">="&B63,'Raw Data'!$B$2:$B$251,"<="&EOMONTH(B63,0)) -> 23039.3 | E63: =$I$57+$I$56*A63 -> 18976.097 | F63: =D63/D62-1 -> 0.87167735
A64: 9 | B64: 45658 | C64: =TEXT(B64,"mmm-yy") -> Jan-25 | D64: =SUMIFS('Raw Data'!$N$2:$N$251,'Raw Data'!$B$2:$B$251,">="&B64,'Raw Data'!$B$2:$B$251,"<="&EOMONTH(B64,0)) -> 25799.15 | E64: =$I$57+$I$56*A64 -> 19314.45 | F64: =D64/D63-1 -> 0.1197888
A65: 10 | B65: 45689 | C65: =TEXT(B65,"mmm-yy") -> Feb-25 | D65: =SUMIFS('Raw Data'!$N$2:$N$251,'Raw Data'!$B$2:$B$251,">="&B65,'Raw Data'!$B$2:$B$251,"<="&EOMONTH(B65,0)) -> 16069.38 | E65: =$I$57+$I$56*A65 -> 19652.802 | F65: =D65/D64-1 -> -0.37713529
A66: 11 | B66: 45717 | C66: =TEXT(B66,"mmm-yy") -> Mar-25 | D66: =SUMIFS('Raw Data'!$N$2:$N$251,'Raw Data'!$B$2:$B$251,">="&B66,'Raw Data'!$B$2:$B$251,"<="&EOMONTH(B66,0)) -> 19899.38 | E66: =$I$57+$I$56*A66 -> 19991.155 | F66: =D66/D65-1 -> 0.23834149
A68: Partial months (excluded from trend): | B68: 45383 | D68: =SUMIFS('Raw Data'!$N$2:$N$251,'Raw Data'!$B$2:$B$251,">="&B68,'Raw Data'!$B$2:$B$251,"<="&EOMONTH(B68,0)) -> 20919.33 | E68: Data starts 11-Apr-2024 and ends 11-Apr-2025, so these two months are incomplete.
B69: 45748 | D69: =SUMIFS('Raw Data'!$N$2:$N$251,'Raw Data'!$B$2:$B$251,">="&B69,'Raw Data'!$B$2:$B$251,"<="&EOMONTH(B69,0)) -> 6979.83
A79: 6. GROUP BY - HIGH-VALUE CUSTOMERS (SUMIFS / COUNTIFS / RANK)
A80: High-value = top X% of customers | B80: 0.2
A81: Revenue cut-off for High Value | B81: =PERCENTILE(D85:D134,1-B80) -> 6557.8
A82: Median customer revenue | B82: =MEDIAN(D85:D134) -> 4254.875
A84: Customer ID | B84: Customer Name | C84: Last Order | D84: Total Revenue | E84: Orders | F84: Avg Order Value | G84: Rank | H84: Segment | I84: Abbreviation | J84: Repeat?
A85: CUST001 | B85: =INDEX('Raw Data'!$D$2:$D$251,MATCH(A85,'Raw Data'!$C$2:$C$251,0)) -> John Smith | C85: =_xlfn.MAXIFS('Raw Data'!$B$2:$B$251,'Raw Data'!$C$2:$C$251,A85) -> 45740 | D85: =SUMIFS('Raw Data'!$N$2:$N$251,'Raw Data'!$C$2:$C$251,A85) -> 599.96 | E85: =COUNTIF('Raw Data'!$C$2:$C$251,A85) -> 1 | F85: =IFERROR(D85/E85,0) -> 599.96 | G85: =RANK(D85,$D$85:$D$134)+COUNTIF($D$85:D85,D85)-1 -> 47 | H85: =IF(D85>=$B$81,"High Value",IF(D85>=$B$82,"Medium","Low")) -> Low | I85: =UPPER(LEFT(B85,1)&MID(B85,FIND(" ",B85)+1,1))&"-"&RIGHT(A85,3) -> JS-001 | J85: =IF(E85>1,"Repeat","One-time") -> One-time
A86: CUST002 | B86: =INDEX('Raw Data'!$D$2:$D$251,MATCH(A86,'Raw Data'!$C$2:$C$251,0)) -> Emma Wilson | C86: =_xlfn.MAXIFS('Raw Data'!$B$2:$B$251,'Raw Data'!$C$2:$C$251,A86) -> 45737 | D86: =SUMIFS('Raw Data'!$N$2:$N$251,'Raw Data'!$C$2:$C$251,A86) -> 1229.88 | E86: =COUNTIF('Raw Data'!$C$2:$C$251,A86) -> 5 | F86: =IFERROR(D86/E86,0) -> 245.976 | G86: =RANK(D86,$D$85:$D$134)+COUNTIF($D$85:D86,D86)-1 -> 44 | H86: =IF(D86>=$B$81,"High Value",IF(D86>=$B$82,"Medium","Low")) -> Low | I86: =UPPER(LEFT(B86,1)&MID(B86,FIND(" ",B86)+1,1))&"-"&RIGHT(A86,3) -> EW-002 | J86: =IF(E86>1,"Repeat","One-time") -> Repeat
A87: CUST003 | B87: =INDEX('Raw Data'!$D$2:$D$251,MATCH(A87,'Raw Data'!$C$2:$C$251,0)) -> Michael Brown | C87: =_xlfn.MAXIFS('Raw Data'!$B$2:$B$251,'Raw Data'!$C$2:$C$251,A87) -> 45707 | D87: =SUMIFS('Raw Data'!$N$2:$N$251,'Raw Data'!$C$2:$C$251,A87) -> 6169.74 | E87: =COUNTIF('Raw Data'!$C$2:$C$251,A87) -> 9 | F87: =IFERROR(D87/E87,0) -> 685.52667 | G87: =RANK(D87,$D$85:$D$134)+COUNTIF($D$85:D87,D87)-1 -> 14 | H87: =IF(D87>=$B$81,"High Value",IF(D87>=$B$82,"Medium","Low")) -> Medium | I87: =UPPER(LEFT(B87,1)&MID(B87,FIND(" ",B87)+1,1))&"-"&RIGHT(A87,3) -> MB-003 | J87: =IF(E87>1,"Repeat","One-time") -> Repeat
A88: CUST004 | B88: =INDEX('Raw Data'!$D$2:$D$251,MATCH(A88,'Raw Data'!$C$2:$C$251,0)) -> Sarah Davis | C88: =_xlfn.MAXIFS('Raw Data'!$B$2:$B$251,'Raw Data'!$C$2:$C$251,A88) -> 45619 | D88: =SUMIFS('Raw Data'!$N$2:$N$251,'Raw Data'!$C$2:$C$251,A88) -> 5499.81 | E88: =COUNTIF('Raw Data'!$C$2:$C$251,A88) -> 5 | F88: =IFERROR(D88/E88,0) -> 1099.962 | G88: =RANK(D88,$D$85:$D$134)+COUNTIF($D$85:D88,D88)-1 -> 19 | H88: =IF(D88>=$B$81,"High Value",IF(D88>=$B$82,"Medium","Low")) -> Medium | I88: =UPPER(LEFT(B88,1)&MID(B88,FIND(" ",B88)+1,1))&"-"&RIGHT(A88,3) -> SD-004 | J88: =IF(E88>1,"Repeat","One-time") -> Repeat
A89: CUST005 | B89: =INDEX('Raw Data'!$D$2:$D$251,MATCH(A89,'Raw Data'!$C$2:$C$251,0)) -> James Johnson | C89: =_xlfn.MAXIFS('Raw Data'!$B$2:$B$251,'Raw Data'!$C$2:$C$251,A89) -> 45635 | D89: =SUMIFS('Raw Data'!$N$2:$N$251,'Raw Data'!$C$2:$C$251,A89) -> 179.97 | E89: =COUNTIF('Raw Data'!$C$2:$C$251,A89) -> 1 | F89: =IFERROR(D89/E89,0) -> 179.97 | G89: =RANK(D89,$D$85:$D$134)+COUNTIF($D$85:D89,D89)-1 -> 50 | H89: =IF(D89>=$B$81,"High Value",IF(D89>=$B$82,"Medium","Low")) -> Low | I89: =UPPER(LEFT(B89,1)&MID(B89,FIND(" ",B89)+1,1))&"-"&RIGHT(A89,3) -> JJ-005 | J89: =IF(E89>1,"Repeat","One-time") -> One-time
A90: CUST006 | B90: =INDEX('Raw Data'!$D$2:$D$251,MATCH(A90,'Raw Data'!$C$2:$C$251,0)) -> Lisa Anderson | C90: =_xlfn.MAXIFS('Raw Data'!$B$2:$B$251,'Raw Data'!$C$2:$C$251,A90) -> 45676 | D90: =SUMIFS('Raw Data'!$N$2:$N$251,'Raw Data'!$C$2:$C$251,A90) -> 2039.8 | E90: =COUNTIF('Raw Data'!$C$2:$C$251,A90) -> 5 | F90: =IFERROR(D90/E90,0) -> 407.96 | G90: =RANK(D90,$D$85:$D$134)+COUNTIF($D$85:D90,D90)-1 -> 36 | H90: =IF(D90>=$B$81,"High Value",IF(D90>=$B$82,"Medium","Low")) -> Low | I90: =UPPER(LEFT(B90,1)&MID(B90,FIND(" ",B90)+1,1))&"-"&RIGHT(A90,3) -> LA-006 | J90: =IF(E90>1,"Repeat","One-time") -> Repeat
A91: CUST007 | B91: =INDEX('Raw Data'!$D$2:$D$251,MATCH(A91,'Raw Data'!$C$2:$C$251,0)) -> David Martinez | C91: =_xlfn.MAXIFS('Raw Data'!$B$2:$B$251,'Raw Data'!$C$2:$C$251,A91) -> 45648 | D91: =SUMIFS('Raw Data'!$N$2:$N$251,'Raw Data'!$C$2:$C$251,A91) -> 1809.84 | E91: =COUNTIF('Raw Data'!$C$2:$C$251,A91) -> 6 | F91: =IFERROR(D91/E91,0) -> 301.64 | G91: =RANK(D91,$D$85:$D$134)+COUNTIF($D$85:D91,D91)-1 -> 39 | H91: =IF(D91>=$B$81,"High Value",IF(D91>=$B$82,"Medium","Low")) -> Low | I91: =UPPER(LEFT(B91,1)&MID(B91,FIND(" ",B91)+1,1))&"-"&RIGHT(A91,3) -> DM-007 | J91: =IF(E91>1,"Repeat","One-time") -> Repeat
A92: CUST008 | B92: =INDEX('Raw Data'!$D$2:$D$251,MATCH(A92,'Raw Data'!$C$2:$C$251,0)) -> Jennifer Taylor | C92: =_xlfn.MAXIFS('Raw Data'!$B$2:$B$251,'Raw Data'!$C$2:$C$251,A92) -> 45635 | D92: =SUMIFS('Raw Data'!$N$2:$N$251,'Raw Data'!$C$2:$C$251,A92) -> 4739.85 | E92: =COUNTIF('Raw Data'!$C$2:$C$251,A92) -> 4 | F92: =IFERROR(D92/E92,0) -> 1184.9625 | G92: =RANK(D92,$D$85:$D$134)+COUNTIF($D$85:D92,D92)-1 -> 24 | H92: =IF(D92>=$B$81,"High Value",IF(D92>=$B$82,"Medium","Low")) -> Medium | I92: =UPPER(LEFT(B92,1)&MID(B92,FIND(" ",B92)+1,1))&"-"&RIGHT(A92,3) -> JT-008 | J92: =IF(E92>1,"Repeat","One-time") -> Repeat
A93: CUST009 | B93: =INDEX('Raw Data'!$D$2:$D$251,MATCH(A93,'Raw Data'!$C$2:$C$251,0)) -> Robert Thomas | C93: =_xlfn.MAXIFS('Raw Data'!$B$2:$B$251,'Raw Data'!$C$2:$C$251,A93) -> 45756 | D93: =SUMIFS('Raw Data'!$N$2:$N$251,'Raw Data'!$C$2:$C$251,A93) -> 3509.9 | E93: =COUNTIF('Raw Data'!$C$2:$C$251,A93) -> 5 | F93: =IFERROR(D93/E93,0) -> 701.98 | G93: =RANK(D93,$D$85:$D$134)+COUNTIF($D$85:D93,D93)-1 -> 32 | H93: =IF(D93>=$B$81,"High Value",IF(D93>=$B$82,"Medium","Low")) -> Low | I93: =UPPER(LEFT(B93,1)&MID(B93,FIND(" ",B93)+1,1))&"-"&RIGHT(A93,3) -> RT-009 | J93: =IF(E93>1,"Repeat","One-time") -> Repeat
A94: CUST010 | B94: =INDEX('Raw Data'!$D$2:$D$251,MATCH(A94,'Raw Data'!$C$2:$C$251,0)) -> Maria Garcia | C94: =_xlfn.MAXIFS('Raw Data'!$B$2:$B$251,'Raw Data'!$C$2:$C$251,A94) -> 45604 | D94: =SUMIFS('Raw Data'!$N$2:$N$251,'Raw Data'!$C$2:$C$251,A94) -> 1909.93 | E94: =COUNTIF('Raw Data'!$C$2:$C$251,A94) -> 4 | F94: =IFERROR(D94/E94,0) -> 477.4825 | G94: =RANK(D94,$D$85:$D$134)+COUNTIF($D$85:D94,D94)-1 -> 38 | H94: =IF(D94>=$B$81,"High Value",IF(D94>=$B$82,"Medium","Low")) -> Low | I94: =UPPER(LEFT(B94,1)&MID(B94,FIND(" ",B94)+1,1))&"-"&RIGHT(A94,3) -> MG-010 | J94: =IF(E94>1,"Repeat","One-time") -> Repeat
A95: CUST011 | B95: =INDEX('Raw Data'!$D$2:$D$251,MATCH(A95,'Raw Data'!$C$2:$C$251,0)) -> William White | C95: =_xlfn.MAXIFS('Raw Data'!$B$2:$B$251,'Raw Data'!$C$2:$C$251,A95) -> 45686 | D95: =SUMIFS('Raw Data'!$N$2:$N$251,'Raw Data'!$C$2:$C$251,A95) -> 4749.91 | E95: =COUNTIF('Raw Data'!$C$2:$C$251,A95) -> 3 | F95: =IFERROR(D95/E95,0) -> 1583.3033 | G95: =RANK(D95,$D$85:$D$134)+COUNTIF($D$85:D95,D95)-1 -> 23 | H95: =IF(D95>=$B$81,"High Value",IF(D95>=$B$82,"Medium","Low")) -> Medium | I95: =UPPER(LEFT(B95,1)&MID(B95,FIND(" ",B95)+1,1))&"-"&RIGHT(A95,3) -> WW-011 | J95: =IF(E95>1,"Repeat","One-time") -> Repeat
A96: CUST012 | B96: =INDEX('Raw Data'!$D$2:$D$251,MATCH(A96,'Raw Data'!$C$2:$C$251,0)) -> Patricia Moore | C96: =_xlfn.MAXIFS('Raw Data'!$B$2:$B$251,'Raw Data'!$C$2:$C$251,A96) -> 45607 | D96: =SUMIFS('Raw Data'!$N$2:$N$251,'Raw Data'!$C$2:$C$251,A96) -> 9799.73 | E96: =COUNTIF('Raw Data'!$C$2:$C$251,A96) -> 8 | F96: =IFERROR(D96/E96,0) -> 1224.9662 | G96: =RANK(D96,$D$85:$D$134)+COUNTIF($D$85:D96,D96)-1 -> 4 | H96: =IF(D96>=$B$81,"High Value",IF(D96>=$B$82,"Medium","Low")) -> High Value | I96: =UPPER(LEFT(B96,1)&MID(B96,FIND(" ",B96)+1,1))&"-"&RIGHT(A96,3) -> PM-012 | J96: =IF(E96>1,"Repeat","One-time") -> Repeat
... A134: CUST050 | B134: =INDEX('Raw Data'!$D$2:$D$251,MATCH(A134,'Raw Data'!$C$2:$C$251,0)) -> Julie Foster | C134: =_xlfn.MAXIFS('Raw Data'!$B$2:$B$251,'Raw Data'!$C$2:$C$251,A134) -> 45452 | D134: =SUMIFS('Raw Data'!$N$2:$N$251,'Raw Data'!$C$2:$C$251,A134) -> 239.96 | E134: =COUNTIF('Raw Data'!$C$2:$C$251,A134) -> 1 | F134: =IFERROR(D134/E134,0) -> 239.96 | G134: =RANK(D134,$D$85:$D$134)+COUNTIF($D$85:D134,D134)-1 -> 49 | H134: =IF(D134>=$B$81,"High Value",IF(D134>=$B$82,"Medium","Low")) -> Low | I134: =UPPER(LEFT(B134,1)&MID(B134,FIND(" ",B134)+1,1))&"-"&RIGHT(A134,3) -> JF-050 | J134: =IF(E134>1,"Repeat","One-time") -> One-time
A136: Top 5 customers
A137: Rank | B137: Customer | C137: Revenue | D137: Segment | E137: Share of total
A138: 1 | B138: =INDEX($B$85:$B$134,MATCH(A138,$G$85:$G$134,0)) -> Mark Carter | C138: =INDEX($D$85:$D$134,MATCH(A138,$G$85:$G$134,0)) -> 15659.65 | D138: =INDEX($H$85:$H$134,MATCH(A138,$G$85:$G$134,0)) -> High Value | E138: =C138/$B$39 -> 0.068325325
A139: 2 | B139: =INDEX($B$85:$B$134,MATCH(A139,$G$85:$G$134,0)) -> Edward Mitchell | C139: =INDEX($D$85:$D$134,MATCH(A139,$G$85:$G$134,0)) -> 11919.77 | D139: =INDEX($H$85:$H$134,MATCH(A139,$G$85:$G$134,0)) -> High Value | E139: =C139/$B$39 -> 0.052007686
A140: 3 | B140: =INDEX($B$85:$B$134,MATCH(A140,$G$85:$G$134,0)) -> Barbara Young | C140: =INDEX($D$85:$D$134,MATCH(A140,$G$85:$G$134,0)) -> 10649.8 | D140: =INDEX($H$85:$H$134,MATCH(A140,$G$85:$G$134,0)) -> High Value | E140: =C140/$B$39 -> 0.046466623
A141: 4 | B141: =INDEX($B$85:$B$134,MATCH(A141,$G$85:$G$134,0)) -> Patricia Moore | C141: =INDEX($D$85:$D$134,MATCH(A141,$G$85:$G$134,0)) -> 9799.73 | D141: =INDEX($H$85:$H$134,MATCH(A141,$G$85:$G$134,0)) -> High Value | E141: =C141/$B$39 -> 0.042757644
A142: 5 | B142: =INDEX($B$85:$B$134,MATCH(A142,$G$85:$G$134,0)) -> Paul Baker | C142: =INDEX($D$85:$D$134,MATCH(A142,$G$85:$G$134,0)) -> 8309.74 | D142: =INDEX($H$85:$H$134,MATCH(A142,$G$85:$G$134,0)) -> High Value | E142: =C142/$B$39 -> 0.036256601
A143: High-value customers (count) | B143: =COUNTIF(H85:H134,"High Value") -> 10 | C143: Their share of revenue | D143: =SUMIF(H85:H134,"High Value",D85:D134)/B39 -> 0.40955822
A146: 7. MOST FREQUENT PRODUCT & REPEATING NAMES (COUNTIF / INDEX-MATCH)
A147: Product | B147: Category | C147: Times Purchased (orders) | D147: Units Sold | E147: Revenue | F147: Revenue Share | G147: Revenue Rank | H147: Product Code
A148: Blender | B148: =INDEX('Raw Data'!$G$2:$G$251,MATCH(A148,'Raw Data'!$F$2:$F$251,0)) -> Appliances | C148: =COUNTIF('Raw Data'!$F$2:$F$251,A148) -> 29 | D148: =SUMIF('Raw Data'!$F$2:$F$251,A148,'Raw Data'!$H$2:$H$251) -> 87 | E148: =SUMIF('Raw Data'!$F$2:$F$251,A148,'Raw Data'!$N$2:$N$251) -> 5219.13 | F148: =E148/SUM($E$148:$E$157) -> 0.022771821 | G148: =RANK(E148,$E$148:$E$157) -> 9 | H148: =UPPER(LEFT(A148,3))&"-"&TEXT(ROW()-147,"00") -> BLE-01
A149: Bookshelf | B149: =INDEX('Raw Data'!$G$2:$G$251,MATCH(A149,'Raw Data'!$F$2:$F$251,0)) -> Furniture | C149: =COUNTIF('Raw Data'!$F$2:$F$251,A149) -> 35 | D149: =SUMIF('Raw Data'!$F$2:$F$251,A149,'Raw Data'!$H$2:$H$251) -> 102 | E149: =SUMIF('Raw Data'!$F$2:$F$251,A149,'Raw Data'!$N$2:$N$251) -> 15298.98 | F149: =E149/SUM($E$148:$E$157) -> 0.066751669 | G149: =RANK(E149,$E$148:$E$157) -> 5 | H149: =UPPER(LEFT(A149,3))&"-"&TEXT(ROW()-147,"00") -> BOO-02
A150: Coffee Maker | B150: =INDEX('Raw Data'!$G$2:$G$251,MATCH(A150,'Raw Data'!$F$2:$F$251,0)) -> Appliances | C150: =COUNTIF('Raw Data'!$F$2:$F$251,A150) -> 14 | D150: =SUMIF('Raw Data'!$F$2:$F$251,A150,'Raw Data'!$H$2:$H$251) -> 39 | E150: =SUMIF('Raw Data'!$F$2:$F$251,A150,'Raw Data'!$N$2:$N$251) -> 3119.61 | F150: =E150/SUM($E$148:$E$157) -> 0.013611311 | G150: =RANK(E150,$E$148:$E$157) -> 10 | H150: =UPPER(LEFT(A150,3))&"-"&TEXT(ROW()-147,"00") -> COF-03
A151: Desk | B151: =INDEX('Raw Data'!$G$2:$G$251,MATCH(A151,'Raw Data'!$F$2:$F$251,0)) -> Furniture | C151: =COUNTIF('Raw Data'!$F$2:$F$251,A151) -> 26 | D151: =SUMIF('Raw Data'!$F$2:$F$251,A151,'Raw Data'!$H$2:$H$251) -> 78 | E151: =SUMIF('Raw Data'!$F$2:$F$251,A151,'Raw Data'!$N$2:$N$251) -> 23399.22 | F151: =E151/SUM($E$148:$E$157) -> 0.10209419 | G151: =RANK(E151,$E$148:$E$157) -> 3 | H151: =UPPER(LEFT(A151,3))&"-"&TEXT(ROW()-147,"00") -> DES-04
A152: Headphones | B152: =INDEX('Raw Data'!$G$2:$G$251,MATCH(A152,'Raw Data'!$F$2:$F$251,0)) -> Electronics | C152: =COUNTIF('Raw Data'!$F$2:$F$251,A152) -> 16 | D152: =SUMIF('Raw Data'!$F$2:$F$251,A152,'Raw Data'!$H$2:$H$251) -> 47 | E152: =SUMIF('Raw Data'!$F$2:$F$251,A152,'Raw Data'!$N$2:$N$251) -> 7049.53 | F152: =E152/SUM($E$148:$E$157) -> 0.030758122 | G152: =RANK(E152,$E$148:$E$157) -> 8 | H152: =UPPER(LEFT(A152,3))&"-"&TEXT(ROW()-147,"00") -> HEA-05
A153: Keyboard | B153: =INDEX('Raw Data'!$G$2:$G$251,MATCH(A153,'Raw Data'!$F$2:$F$251,0)) -> Electronics | C153: =COUNTIF('Raw Data'!$F$2:$F$251,A153) -> 34 | D153: =SUMIF('Raw Data'!$F$2:$F$251,A153,'Raw Data'!$H$2:$H$251) -> 89 | E153: =SUMIF('Raw Data'!$F$2:$F$251,A153,'Raw Data'!$N$2:$N$251) -> 8009.11 | F153: =E153/SUM($E$148:$E$157) -> 0.034944909 | G153: =RANK(E153,$E$148:$E$157) -> 7 | H153: =UPPER(LEFT(A153,3))&"-"&TEXT(ROW()-147,"00") -> KEY-06
A154: Laptop | B154: =INDEX('Raw Data'!$G$2:$G$251,MATCH(A154,'Raw Data'!$F$2:$F$251,0)) -> Electronics | C154: =COUNTIF('Raw Data'!$F$2:$F$251,A154) -> 24 | D154: =SUMIF('Raw Data'!$F$2:$F$251,A154,'Raw Data'!$H$2:$H$251) -> 75 | E154: =SUMIF('Raw Data'!$F$2:$F$251,A154,'Raw Data'!$N$2:$N$251) -> 67499.25 | F154: =E154/SUM($E$148:$E$157) -> 0.29450902 | G154: =RANK(E154,$E$148:$E$157) -> 1 | H154: =UPPER(LEFT(A154,3))&"-"&TEXT(ROW()-147,"00") -> LAP-07
A155: Monitor | B155: =INDEX('Raw Data'!$G$2:$G$251,MATCH(A155,'Raw Data'!$F$2:$F$251,0)) -> Electronics | C155: =COUNTIF('Raw Data'!$F$2:$F$251,A155) -> 26 | D155: =SUMIF('Raw Data'!$F$2:$F$251,A155,'Raw Data'!$H$2:$H$251) -> 88 | E155: =SUMIF('Raw Data'!$F$2:$F$251,A155,'Raw Data'!$N$2:$N$251) -> 21999.12 | F155: =E155/SUM($E$148:$E$157) -> 0.095985352 | G155: =RANK(E155,$E$148:$E$157) -> 4 | H155: =UPPER(LEFT(A155,3))&"-"&TEXT(ROW()-147,"00") -> MON-08
A156: Office Chair | B156: =INDEX('Raw Data'!$G$2:$G$251,MATCH(A156,'Raw Data'!$F$2:$F$251,0)) -> Furniture | C156: =COUNTIF('Raw Data'!$F$2:$F$251,A156) -> 15 | D156: =SUMIF('Raw Data'!$F$2:$F$251,A156,'Raw Data'!$H$2:$H$251) -> 52 | E156: =SUMIF('Raw Data'!$F$2:$F$251,A156,'Raw Data'!$N$2:$N$251) -> 10399.48 | F156: =E156/SUM($E$148:$E$157) -> 0.04537444 | G156: =RANK(E156,$E$148:$E$157) -> 6 | H156: =UPPER(LEFT(A156,3))&"-"&TEXT(ROW()-147,"00") -> OFF-09
A157: Smartphone | B157: =INDEX('Raw Data'!$G$2:$G$251,MATCH(A157,'Raw Data'!$F$2:$F$251,0)) -> Electronics | C157: =COUNTIF('Raw Data'!$F$2:$F$251,A157) -> 31 | D157: =SUMIF('Raw Data'!$F$2:$F$251,A157,'Raw Data'!$H$2:$H$251) -> 96 | E157: =SUMIF('Raw Data'!$F$2:$F$251,A157,'Raw Data'!$N$2:$N$251) -> 67199.04 | F157: =E157/SUM($E$148:$E$157) -> 0.29319916 | G157: =RANK(E157,$E$148:$E$157) -> 2 | H157: =UPPER(LEFT(A157,3))&"-"&TEXT(ROW()-147,"00") -> SMA-10
A159: Most frequently purchased product | B159: =INDEX(A148:A157,MATCH(MAX(C148:C157),C148:C157,0)) -> Bookshelf
...

Sheet Visualizations
A1: VISUALIZATIONS - charts built from the Analysis sheet

Sheet Dashboard
B1: DATA INTELLIGENCE DASHBOARD
B2: ="Customer transactions | Data: "&TEXT(Analysis!B6,"dd mmm yyyy")&" to "&TEXT(Analysis!B7,"dd mmm yyyy")&" | Opened "&TEXT(NOW(),"dd mmm yyyy hh:mm") -> Customer transactions | Data: 11 Apr 2024 to 11 Apr 2025 | Opened 12 Oct 2026 06:35
B4: REGION | C4: All | F4: CATEGORY | G4: All | J4: PAYMENT | K4: All
B5: Pick a value from the yellow dropdowns - every card and chart below updates. Choose All to reset.
B7: TOTAL REVENUE | E7: ORDERS | H7: UNITS SOLD | K7: AVG ORDER VALUE
B8: ='Dash Data'!B8 -> 229192.47 | E8: ='Dash Data'!B9 -> 250 | H8: ='Dash Data'!B10 -> 753 | K8: ='Dash Data'!B11 -> 916.76988
B9: =TEXT('Dash Data'!B12,"0.0%")&" of all revenue" -> 100.0% of all revenue | E9: ="Avg order "&TEXT('Dash Data'!B11,"$#,##0") -> Avg order $917 | H9: =IFERROR(TEXT('Dash Data'!B10/'Dash Data'!B9,"0.0"),"0")&" units per order" -> 3.0 units per order | K9: =IFERROR(TEXT('Dash Data'!B11/'Dash Data'!B13-1,"+0%;-0%")&" vs overall","-") -> +0% vs overall
B11: MONTH-ON-MONTH GROWTH | E11: LAST MONTH vs AVERAGE | H11: TOP PRODUCT | K11: TOP CUSTOMER
B12: ='Dash Data'!B16 -> 0.23834149 | E12: ='Dash Data'!B18 -> 1.087434 | H12: ='Dash Data'!B19 -> Laptop | K12: ='Dash Data'!B21 -> Mark Carter
B13: ='Dash Data'!B38&" vs "&'Dash Data'!B37 -> Mar-25 vs Feb-25 | E13: ="Avg month "&TEXT('Dash Data'!B17,"$#,##0") -> Avg month $18,299 | H13: =TEXT('Dash Data'!B20,"$#,##0")&" revenue" -> $67,499 revenue | K13: =TEXT('Dash Data'!B22,"$#,##0")&" revenue" -> $15,660 revenue
B15: =IF('Dash Data'!B9=0,"No transactions match this selection - change a filter.","Showing "&IF(C4="All","all regions",C4&" region")&", "&IF(G4="All","all categories",G4)&", "&IF(K4="All","all payment methods",K4&" payments")&": "&TEXT('Dash Data'!B8,"$#,##0")&" revenue from "&'Dash Data'!B9&" orders. Best month: "&'Dash Data'!B23&".") -> Showing all regions, all categories, all payment methods: $229,192 revenue from 250 orders. Best month: Jan-25.
B65: Note: Apr-2024 and Apr-2025 are partial months (data runs 11-Apr-2024 to 11-Apr-2025), so monthly figures use full months May-2024 to Mar-2025.

Sheet Dash Data
A1: DASHBOARD ENGINE - do not edit. It reads the dropdowns on the Dashboard sheet.
A3: Region criteria | B3: =IF(Dashboard!C4="All","*",Dashboard!C4) -> *
A4: Category criteria | B4: =IF(Dashboard!G4="All","*",Dashboard!G4) -> *
A5: Payment criteria | B5: =IF(Dashboard!K4="All","*",Dashboard!K4) -> *
A8: Revenue (selection) | B8: =SUMIFS('Raw Data'!$N$2:$N$251,'Raw Data'!$K$2:$K$251,$B$3,'Raw Data'!$G$2:$G$251,$B$4,'Raw Data'!$J$2:$J$251,$B$5) -> 229192.47
A9: Orders | B9: =COUNTIFS('Raw Data'!$K$2:$K$251,$B$3,'Raw Data'!$G$2:$G$251,$B$4,'Raw Data'!$J$2:$J$251,$B$5) -> 250
A10: Units sold | B10: =SUMIFS('Raw Data'!$H$2:$H$251,'Raw Data'!$K$2:$K$251,$B$3,'Raw Data'!$G$2:$G$251,$B$4,'Raw Data'!$J$2:$J$251,$B$5) -> 753
A11: Average order value | B11: =IFERROR(B8/B9,0) -> 916.76988
A12: Share of all revenue | B12: =B8/Analysis!B39 -> 1
A13: Overall avg order value | B13: =Analysis!E180 -> 916.76988
A14: Last full month revenue | B14: =C38 -> 19899.38
A15: Previous month revenue | B15: =C37 -> 16069.38
A16: Month-on-month growth | B16: =IFERROR(B14/B15-1,0) -> 0.23834149
A17: Average full month | B17: =AVERAGE(C28:C38) -> 18299.392
A18: Last month vs average | B18: =IFERROR(B14/B17,0) -> 1.087434
A19: Top product | B19: =IF(H43=0,"-",G43) -> Laptop
A20: Top product revenue | B20: =H43 -> 67499.25
A21: Top customer | B21: =IF(H82=0,"-",G82) -> Mark Carter
A22: Top customer revenue | B22: =H82 -> 15659.65
A23: Best month | B23: =IF(B8=0,"-",INDEX(B28:B38,MATCH(MAX(C28:C38),C28:C38,0))) -> Jan-25
A27: Month Start | B27: Label | C27: Revenue | D27: MoM %
A28: 45413 | B28: =TEXT(A28,"mmm-yy") -> May-24 | C28: =SUMIFS('Raw Data'!$N$2:$N$251,'Raw Data'!$B$2:$B$251,">="&A28,'Raw Data'!$B$2:$B$251,"<="&EOMONTH(A28,0),'Raw Data'!$K$2:$K$251,$B$3,'Raw Data'!$G$2:$G$251,$B$4,'Raw Data'!$J$2:$J$251,$B$5) -> 17039.35
A29: 45444 | B29: =TEXT(A29,"mmm-yy") -> Jun-24 | C29: =SUMIFS('Raw Data'!$N$2:$N$251,'Raw Data'!$B$2:$B$251,">="&A29,'Raw Data'!$B$2:$B$251,"<="&EOMONTH(A29,0),'Raw Data'!$K$2:$K$251,$B$3,'Raw Data'!$G$2:$G$251,$B$4,'Raw Data'!$J$2:$J$251,$B$5) -> 19299.45 | D29: =IFERROR(C29/C28-1,0) -> 0.13264004
A30: 45474 | B30: =TEXT(A30,"mmm-yy") -> Jul-24 | C30: =SUMIFS('Raw Data'!$N$2:$N$251,'Raw Data'!$B$2:$B$251,">="&A30,'Raw Data'!$B$2:$B$251,"<="&EOMONTH(A30,0),'Raw Data'!$K$2:$K$251,$B$3,'Raw Data'!$G$2:$G$251,$B$4,'Raw Data'!$J$2:$J$251,$B$5) -> 18479.4 | D30: =IFERROR(C30/C29-1,0) -> -0.042490848
A31: 45505 | B31: =TEXT(A31,"mmm-yy") -> Aug-24 | C31: =SUMIFS('Raw Data'!$N$2:$N$251,'Raw Data'!$B$2:$B$251,">="&A31,'Raw Data'!$B$2:$B$251,"<="&EOMONTH(A31,0),'Raw Data'!$K$2:$K$251,$B$3,'Raw Data'!$G$2:$G$251,$B$4,'Raw Data'!$J$2:$J$251,$B$5) -> 15759.43 | D31: =IFERROR(C31/C30-1,0) -> -0.1471893
A32: 45536 | B32: =TEXT(A32,"mmm-yy") -> Sep-24 | C32: =SUMIFS('Raw Data'!$N$2:$N$251,'Raw Data'!$B$2:$B$251,">="&A32,'Raw Data'!$B$2:$B$251,"<="&EOMONTH(A32,0),'Raw Data'!$K$2:$K$251,$B$3,'Raw Data'!$G$2:$G$251,$B$4,'Raw Data'!$J$2:$J$251,$B$5) -> 12989.51 | D32: =IFERROR(C32/C31-1,0) -> -0.1757627
A33: 45566 | B33: =TEXT(A33,"mmm-yy") -> Oct-24 | C33: =SUMIFS('Raw Data'!$N$2:$N$251,'Raw Data'!$B$2:$B$251,">="&A33,'Raw Data'!$B$2:$B$251,"<="&EOMONTH(A33,0),'Raw Data'!$K$2:$K$251,$B$3,'Raw Data'!$G$2:$G$251,$B$4,'Raw Data'!$J$2:$J$251,$B$5) -> 20609.52 | D33: =IFERROR(C33/C32-1,0) -> 0.58662798
A34: 45597 | B34: =TEXT(A34,"mmm-yy") -> Nov-24 | C34: =SUMIFS('Raw Data'!$N$2:$N$251,'Raw Data'!$B$2:$B$251,">="&A34,'Raw Data'!$B$2:$B$251,"<="&EOMONTH(A34,0),'Raw Data'!$K$2:$K$251,$B$3,'Raw Data'!$G$2:$G$251,$B$4,'Raw Data'!$J$2:$J$251,$B$5) -> 12309.44 | D34: =IFERROR(C34/C33-1,0) -> -0.40273039
A35: 45627 | B35: =TEXT(A35,"mmm-yy") -> Dec-24 | C35: =SUMIFS('Raw Data'!$N$2:$N$251,'Raw Data'!$B$2:$B$251,">="&A35,'Raw Data'!$B$2:$B$251,"<="&EOMONTH(A35,0),'Raw Data'!$K$2:$K$251,$B$3,'Raw Data'!$G$2:$G$251,$B$4,'Raw Data'!$J$2:$J$251,$B$5) -> 23039.3 | D35: =IFERROR(C35/C34-1,0) -> 0.87167735
A36: 45658 | B36: =TEXT(A36,"mmm-yy") -> Jan-25 | C36: =SUMIFS('Raw Data'!$N$2:$N$251,'Raw Data'!$B$2:$B$251,">="&A36,'Raw Data'!$B$2:$B$251,"<="&EOMONTH(A36,0),'Raw Data'!$K$2:$K$251,$B$3,'Raw Data'!$G$2:$G$251,$B$4,'Raw Data'!$J$2:$J$251,$B$5) -> 25799.15 | D36: =IFERROR(C36/C35-1,0) -> 0.1197888
A37: 45689 | B37: =TEXT(A37,"mmm-yy") -> Feb-25 | C37: =SUMIFS('Raw Data'!$N$2:$N$251,'Raw Data'!$B$2:$B$251,">="&A37,'Raw Data'!$B$2:$B$251,"<="&EOMONTH(A37,0),'Raw Data'!$K$2:$K$251,$B$3,'Raw Data'!$G$2:$G$251,$B$4,'Raw Data'!$J$2:$J$251,$B$5) -> 16069.38 | D37: =IFERROR(C37/C36-1,0) -> -0.37713529
A38: 45717 | B38: =TEXT(A38,"mmm-yy") -> Mar-25 | C38: =SUMIFS('Raw Data'!$N$2:$N$251,'Raw Data'!$B$2:$B$251,">="&A38,'Raw Data'!$B$2:$B$251,"<="&EOMONTH(A38,0),'Raw Data'!$K$2:$K$251,$B$3,'Raw Data'!$G$2:$G$251,$B$4,'Raw Data'!$J$2:$J$251,$B$5) -> 19899.38 | D38: =IFERROR(C38/C37-1,0) -> 0.23834149
A42: Product | B42: Revenue | C42: Units | D42: Rank | F42: Rank | G42: Product (sorted) | H42: Revenue
A43: Blender | B43: =SUMIFS('Raw Data'!$N$2:$N$251,'Raw Data'!$F$2:$F$251,A43,'Raw Data'!$K$2:$K$251,$B$3,'Raw Data'!$G$2:$G$251,$B$4,'Raw Data'!$J$2:$J$251,$B$5) -> 5219.13 | C43: =SUMIFS('Raw Data'!$H$2:$H$251,'Raw Data'!$F$2:$F$251,A43,'Raw Data'!$K$2:$K$251,$B$3,'Raw Data'!$G$2:$G$251,$B$4,'Raw Data'!$J$2:$J$251,$B$5) -> 87 | D43: =RANK(B43,$B$43:$B$52)+COUNTIF($B$43:B43,B43)-1 -> 9 | F43: 1 | G43: =INDEX($A$43:$A$52,MATCH(F43,$D$43:$D$52,0)) -> Laptop | H43: =INDEX($B$43:$B$52,MATCH(F43,$D$43:$D$52,0)) -> 67499.25
A44: Bookshelf | B44: =SUMIFS('Raw Data'!$N$2:$N$251,'Raw Data'!$F$2:$F$251,A44,'Raw Data'!$K$2:$K$251,$B$3,'Raw Data'!$G$2:$G$251,$B$4,'Raw Data'!$J$2:$J$251,$B$5) -> 15298.98 | C44: =SUMIFS('Raw Data'!$H$2:$H$251,'Raw Data'!$F$2:$F$251,A44,'Raw Data'!$K$2:$K$251,$B$3,'Raw Data'!$G$2:$G$251,$B$4,'Raw Data'!$J$2:$J$251,$B$5) -> 102 | D44: =RANK(B44,$B$43:$B$52)+COUNTIF($B$43:B44,B44)-1 -> 5 | F44: 2 | G44: =INDEX($A$43:$A$52,MATCH(F44,$D$43:$D$52,0)) -> Smartphone | H44: =INDEX($B$43:$B$52,MATCH(F44,$D$43:$D$52,0)) -> 67199.04
A45: Coffee Maker | B45: =SUMIFS('Raw Data'!$N$2:$N$251,'Raw Data'!$F$2:$F$251,A45,'Raw Data'!$K$2:$K$251,$B$3,'Raw Data'!$G$2:$G$251,$B$4,'Raw Data'!$J$2:$J$251,$B$5) -> 3119.61 | C45: =SUMIFS('Raw Data'!$H$2:$H$251,'Raw Data'!$F$2:$F$251,A45,'Raw Data'!$K$2:$K$251,$B$3,'Raw Data'!$G$2:$G$251,$B$4,'Raw Data'!$J$2:$J$251,$B$5) -> 39 | D45: =RANK(B45,$B$43:$B$52)+COUNTIF($B$43:B45,B45)-1 -> 10 | F45: 3 | G45: =INDEX($A$43:$A$52,MATCH(F45,$D$43:$D$52,0)) -> Desk | H45: =INDEX($B$43:$B$52,MATCH(F45,$D$43:$D$52,0)) -> 23399.22
A46: Desk | B46: =SUMIFS('Raw Data'!$N$2:$N$251,'Raw Data'!$F$2:$F$251,A46,'Raw Data'!$K$2:$K$251,$B$3,'Raw Data'!$G$2:$G$251,$B$4,'Raw Data'!$J$2:$J$251,$B$5) -> 23399.22 | C46: =SUMIFS('Raw Data'!$H$2:$H$251,'Raw Data'!$F$2:$F$251,A46,'Raw Data'!$K$2:$K$251,$B$3,'Raw Data'!$G$2:$G$251,$B$4,'Raw Data'!$J$2:$J$251,$B$5) -> 78 | D46: =RANK(B46,$B$43:$B$52)+COUNTIF($B$43:B46,B46)-1 -> 3 | F46: 4 | G46: =INDEX($A$43:$A$52,MATCH(F46,$D$43:$D$52,0)) -> Monitor | H46: =INDEX($B$43:$B$52,MATCH(F46,$D$43:$D$52,0)) -> 21999.12
A47: Headphones | B47: =SUMIFS('Raw Data'!$N$2:$N$251,'Raw Data'!$F$2:$F$251,A47,'Raw Data'!$K$2:$K$251,$B$3,'Raw Data'!$G$2:$G$251,$B$4,'Raw Data'!$J$2:$J$251,$B$5) -> 7049.53 | C47: =SUMIFS('Raw Data'!$H$2:$H$251,'Raw Data'!$F$2:$F$251,A47,'Raw Data'!$K$2:$K$251,$B$3,'Raw Data'!$G$2:$G$251,$B$4,'Raw Data'!$J$2:$J$251,$B$5) -> 47 | D47: =RANK(B47,$B$43:$B$52)+COUNTIF($B$43:B47,B47)-1 -> 8 | F47: 5 | G47: =INDEX($A$43:$A$52,MATCH(F47,$D$43:$D$52,0)) -> Bookshelf | H47: =INDEX($B$43:$B$52,MATCH(F47,$D$43:$D$52,0)) -> 15298.98
A48: Keyboard | B48: =SUMIFS('Raw Data'!$N$2:$N$251,'Raw Data'!$F$2:$F$251,A48,'Raw Data'!$K$2:$K$251,$B$3,'Raw Data'!$G$2:$G$251,$B$4,'Raw Data'!$J$2:$J$251,$B$5) -> 8009.11 | C48: =SUMIFS('Raw Data'!$H$2:$H$251,'Raw Data'!$F$2:$F$251,A48,'Raw Data'!$K$2:$K$251,$B$3,'Raw Data'!$G$2:$G$251,$B$4,'Raw Data'!$J$2:$J$251,$B$5) -> 89 | D48: =RANK(B48,$B$43:$B$52)+COUNTIF($B$43:B48,B48)-1 -> 7 | F48: 6 | G48: =INDEX($A$43:$A$52,MATCH(F48,$D$43:$D$52,0)) -> Office Chair | H48: =INDEX($B$43:$B$52,MATCH(F48,$D$43:$D$52,0)) -> 10399.48
A49: Laptop | B49: =SUMIFS('Raw Data'!$N$2:$N$251,'Raw Data'!$F$2:$F$251,A49,'Raw Data'!$K$2:$K$251,$B$3,'Raw Data'!$G$2:$G$251,$B$4,'Raw Data'!$J$2:$J$251,$B$5) -> 67499.25 | C49: =SUMIFS('Raw Data'!$H$2:$H$251,'Raw Data'!$F$2:$F$251,A49,'Raw Data'!$K$2:$K$251,$B$3,'Raw Data'!$G$2:$G$251,$B$4,'Raw Data'!$J$2:$J$251,$B$5) -> 75 | D49: =RANK(B49,$B$43:$B$52)+COUNTIF($B$43:B49,B49)-1 -> 1 | F49: 7 | G49: =INDEX($A$43:$A$52,MATCH(F49,$D$43:$D$52,0)) -> Keyboard | H49: =INDEX($B$43:$B$52,MATCH(F49,$D$43:$D$52,0)) -> 8009.11
A50: Monitor | B50: =SUMIFS('Raw Data'!$N$2:$N$251,'Raw Data'!$F$2:$F$251,A50,'Raw Data'!$K$2:$K$251,$B$3,'Raw Data'!$G$2:$G$251,$B$4,'Raw Data'!$J$2:$J$251,$B$5) -> 21999.12 | C50: =SUMIFS('Raw Data'!$H$2:$H$251,'Raw Data'!$F$2:$F$251,A50,'Raw Data'!$K$2:$K$251,$B$3,'Raw Data'!$G$2:$G$251,$B$4,'Raw Data'!$J$2:$J$251,$B$5) -> 88 | D50: =RANK(B50,$B$43:$B$52)+COUNTIF($B$43:B50,B50)-1 -> 4 | F50: 8 | G50: =INDEX($A$43:$A$52,MATCH(F50,$D$43:$D$52,0)) -> Headphones | H50: =INDEX($B$43:$B$52,MATCH(F50,$D$43:$D$52,0)) -> 7049.53
A51: Office Chair | B51: =SUMIFS('Raw Data'!$N$2:$N$251,'Raw Data'!$F$2:$F$251,A51,'Raw Data'!$K$2:$K$251,$B$3,'Raw Data'!$G$2:$G$251,$B$4,'Raw Data'!$J$2:$J$251,$B$5) -> 10399.48 | C51: =SUMIFS('Raw Data'!$H$2:$H$251,'Raw Data'!$F$2:$F$251,A51,'Raw Data'!$K$2:$K$251,$B$3,'Raw Data'!$G$2:$G$251,$B$4,'Raw Data'!$J$2:$J$251,$B$5) -> 52 | D51: =RANK(B51,$B$43:$B$52)+COUNTIF($B$43:B51,B51)-1 -> 6 | F51: 9 | G51: =INDEX($A$43:$A$52,MATCH(F51,$D$43:$D$52,0)) -> Blender | H51: =INDEX($B$43:$B$52,MATCH(F51,$D$43:$D$52,0)) -> 5219.13
A52: Smartphone | B52: =SUMIFS('Raw Data'!$N$2:$N$251,'Raw Data'!$F$2:$F$251,A52,'Raw Data'!$K$2:$K$251,$B$3,'Raw Data'!$G$2:$G$251,$B$4,'Raw Data'!$J$2:$J$251,$B$5) -> 67199.04 | C52: =SUMIFS('Raw Data'!$H$2:$H$251,'Raw Data'!$F$2:$F$251,A52,'Raw Data'!$K$2:$K$251,$B$3,'Raw Data'!$G$2:$G$251,$B$4,'Raw Data'!$J$2:$J$251,$B$5) -> 96 | D52: =RANK(B52,$B$43:$B$52)+COUNTIF($B$43:B52,B52)-1 -> 2 | F52: 10 | G52: =INDEX($A$43:$A$52,MATCH(F52,$D$43:$D$52,0)) -> Coffee Maker | H52: =INDEX($B$43:$B$52,MATCH(F52,$D$43:$D$52,0)) -> 3119.61
A57: Region | B57: Revenue
A58: Central | B58: =SUMIFS('Raw Data'!$N$2:$N$251,'Raw Data'!$K$2:$K$251,A58,'Raw Data'!$K$2:$K$251,$B$3,'Raw Data'!$G$2:$G$251,$B$4,'Raw Data'!$J$2:$J$251,$B$5) -> 41288.34
A59: East | B59: =SUMIFS('Raw Data'!$N$2:$N$251,'Raw Data'!$K$2:$K$251,A59,'Raw Data'!$K$2:$K$251,$B$3,'Raw Data'!$G$2:$G$251,$B$4,'Raw Data'!$J$2:$J$251,$B$5) -> 59288.39
A60: North | B60: =SUMIFS('Raw Data'!$N$2:$N$251,'Raw Data'!$K$2:$K$251,A60,'Raw Data'!$K$2:$K$251,$B$3,'Raw Data'!$G$2:$G$251,$B$4,'Raw Data'!$J$2:$J$251,$B$5) -> 50808.31
A61: South | B61: =SUMIFS('Raw Data'!$N$2:$N$251,'Raw Data'!$K$2:$K$251,A61,'Raw Data'!$K$2:$K$251,$B$3,'Raw Data'!$G$2:$G$251,$B$4,'Raw Data'!$J$2:$J$251,$B$5) -> 36398.75
A62: West | B62: =SUMIFS('Raw Data'!$N$2:$N$251,'Raw Data'!$K$2:$K$251,A62,'Raw Data'!$K$2:$K$251,$B$3,'Raw Data'!$G$2:$G$251,$B$4,'Raw Data'!$J$2:$J$251,$B$5) -> 41408.68
A66: Category | B66: Revenue
A67: Appliances | B67: =SUMIFS('Raw Data'!$N$2:$N$251,'Raw Data'!$G$2:$G$251,A67,'Raw Data'!$K$2:$K$251,$B$3,'Raw Data'!$G$2:$G$251,$B$4,'Raw Data'!$J$2:$J$251,$B$5) -> 8338.74
A68: Electronics | B68: =SUMIFS('Raw Data'!$N$2:$N$251,'Raw Data'!$G$2:$G$251,A68,'Raw Data'!$K$2:$K$251,$B$3,'Raw Data'!$G$2:$G$251,$B$4,'Raw Data'!$J$2:$J$251,$B$5) -> 171756.05
A69: Furniture | B69: =SUMIFS('Raw Data'!$N$2:$N$251,'Raw Data'!$G$2:$G$251,A69,'Raw Data'!$K$2:$K$251,$B$3,'Raw Data'!$G$2:$G$251,$B$4,'Raw Data'!$J$2:$J$251,$B$5) -> 49097.68
A73: Payment Method | B73: Revenue
A74: Cash | B74: =SUMIFS('Raw Data'!$N$2:$N$251,'Raw Data'!$J$2:$J$251,A74,'Raw Data'!$K$2:$K$251,$B$3,'Raw Data'!$G$2:$G$251,$B$4,'Raw Data'!$J$2:$J$251,$B$5) -> 57427.79
A75: Credit Card | B75: =SUMIFS('Raw Data'!$N$2:$N$251,'Raw Data'!$J$2:$J$251,A75,'Raw Data'!$K$2:$K$251,$B$3,'Raw Data'!$G$2:$G$251,$B$4,'Raw Data'!$J$2:$J$251,$B$5) -> 61447.96
A76: Debit Card | B76: =SUMIFS('Raw Data'!$N$2:$N$251,'Raw Data'!$J$2:$J$251,A76,'Raw Data'!$K$2:$K$251,$B$3,'Raw Data'!$G$2:$G$251,$B$4,'Raw Data'!$J$2:$J$251,$B$5) -> 52118.31
A77: PayPal | B77: =SUMIFS('Raw Data'!$N$2:$N$251,'Raw Data'!$J$2:$J$251,A77,'Raw Data'!$K$2:$K$251,$B$3,'Raw Data'!$G$2:$G$251,$B$4,'Raw Data'!$J$2:$J$251,$B$5) -> 58198.41
A81: Customer | B81: Customer ID | C81: Revenue | D81: Rank | F81: Rank | G81: Top customers | H81: Revenue
A82: =Analysis!B85 -> John Smith | B82: =Analysis!A85 -> CUST001 | C82: =SUMIFS('Raw Data'!$N$2:$N$251,'Raw Data'!$C$2:$C$251,B82,'Raw Data'!$K$2:$K$251,$B$3,'Raw Data'!$G$2:$G$251,$B$4,'Raw Data'!$J$2:$J$251,$B$5) -> 599.96 | D82: =RANK(C82,$C$82:$C$131)+COUNTIF($C$82:C82,C82)-1 -> 47 | F82: 1 | G82: =INDEX($A$82:$A$131,MATCH(F82,$D$82:$D$131,0)) -> Mark Carter | H82: =INDEX($C$82:$C$131,MATCH(F82,$D$82:$D$131,0)) -> 15659.65
A83: =Analysis!B86 -> Emma Wilson | B83: =Analysis!A86 -> CUST002 | C83: =SUMIFS('Raw Data'!$N$2:$N$251,'Raw Data'!$C$2:$C$251,B83,'Raw Data'!$K$2:$K$251,$B$3,'Raw Data'!$G$2:$G$251,$B$4,'Raw Data'!$J$2:$J$251,$B$5) -> 1229.88 | D83: =RANK(C83,$C$82:$C$131)+COUNTIF($C$82:C83,C83)-1 -> 44 | F83: 2 | G83: =INDEX($A$82:$A$131,MATCH(F83,$D$82:$D$131,0)) -> Edward Mitchell | H83: =INDEX($C$82:$C$131,MATCH(F83,$D$82:$D$131,0)) -> 11919.77
A84: =Analysis!B87 -> Michael Brown | B84: =Analysis!A87 -> CUST003 | C84: =SUMIFS('Raw Data'!$N$2:$N$251,'Raw Data'!$C$2:$C$251,B84,'Raw Data'!$K$2:$K$251,$B$3,'Raw Data'!$G$2:$G$251,$B$4,'Raw Data'!$J$2:$J$251,$B$5) -> 6169.74 | D84: =RANK(C84,$C$82:$C$131)+COUNTIF($C$82:C84,C84)-1 -> 14 | F84: 3 | G84: =INDEX($A$82:$A$131,MATCH(F84,$D$82:$D$131,0)) -> Barbara Young | H84: =INDEX($C$82:$C$131,MATCH(F84,$D$82:$D$131,0)) -> 10649.8
A85: =Analysis!B88 -> Sarah Davis | B85: =Analysis!A88 -> CUST004 | C85: =SUMIFS('Raw Data'!$N$2:$N$251,'Raw Data'!$C$2:$C$251,B85,'Raw Data'!$K$2:$K$251,$B$3,'Raw Data'!$G$2:$G$251,$B$4,'Raw Data'!$J$2:$J$251,$B$5) -> 5499.81 | D85: =RANK(C85,$C$82:$C$131)+COUNTIF($C$82:C85,C85)-1 -> 19 | F85: 4 | G85: =INDEX($A$82:$A$131,MATCH(F85,$D$82:$D$131,0)) -> Patricia Moore | H85: =INDEX($C$82:$C$131,MATCH(F85,$D$82:$D$131,0)) -> 9799.73
A86: =Analysis!B89 -> James Johnson | B86: =Analysis!A89 -> CUST005 | C86: =SUMIFS('Raw Data'!$N$2:$N$251,'Raw Data'!$C$2:$C$251,B86,'Raw Data'!$K$2:$K$251,$B$3,'Raw Data'!$G$2:$G$251,$B$4,'Raw Data'!$J$2:$J$251,$B$5) -> 179.97 | D86: =RANK(C86,$C$82:$C$131)+COUNTIF($C$82:C86,C86)-1 -> 50 | F86: 5 | G86: =INDEX($A$82:$A$131,MATCH(F86,$D$82:$D$131,0)) -> Paul Baker | H86: =INDEX($C$82:$C$131,MATCH(F86,$D$82:$D$131,0)) -> 8309.74
A87: =Analysis!B90 -> Lisa Anderson | B87: =Analysis!A90 -> CUST006 | C87: =SUMIFS('Raw Data'!$N$2:$N$251,'Raw Data'!$C$2:$C$251,B87,'Raw Data'!$K$2:$K$251,$B$3,'Raw Data'!$G$2:$G$251,$B$4,'Raw Data'!$J$2:$J$251,$B$5) -> 2039.8 | D87: =RANK(C87,$C$82:$C$131)+COUNTIF($C$82:C87,C87)-1 -> 36
A88: =Analysis!B91 -> David Martinez | B88: =Analysis!A91 -> CUST007 | C88: =SUMIFS('Raw Data'!$N$2:$N$251,'Raw Data'!$C$2:$C$251,B88,'Raw Data'!$K$2:$K$251,$B$3,'Raw Data'!$G$2:$G$251,$B$4,'Raw Data'!$J$2:$J$251,$B$5) -> 1809.84 | D88: =RANK(C88,$C$82:$C$131)+COUNTIF($C$82:C88,C88)-1 -> 39
A89: =Analysis!B92 -> Jennifer Taylor | B89: =Analysis!A92 -> CUST008 | C89: =SUMIFS('Raw Data'!$N$2:$N$251,'Raw Data'!$C$2:$C$251,B89,'Raw Data'!$K$2:$K$251,$B$3,'Raw Data'!$G$2:$G$251,$B$4,'Raw Data'!$J$2:$J$251,$B$5) -> 4739.85 | D89: =RANK(C89,$C$82:$C$131)+COUNTIF($C$82:C89,C89)-1 -> 24
A90: =Analysis!B93 -> Robert Thomas | B90: =Analysis!A93 -> CUST009 | C90: =SUMIFS('Raw Data'!$N$2:$N$251,'Raw Data'!$C$2:$C$251,B90,'Raw Data'!$K$2:$K$251,$B$3,'Raw Data'!$G$2:$G$251,$B$4,'Raw Data'!$J$2:$J$251,$B$5) -> 3509.9 | D90: =RANK(C90,$C$82:$C$131)+COUNTIF($C$82:C90,C90)-1 -> 32
A91: =Analysis!B94 -> Maria Garcia | B91: =Analysis!A94 -> CUST010 | C91: =SUMIFS('Raw Data'!$N$2:$N$251,'Raw Data'!$C$2:$C$251,B91,'Raw Data'!$K$2:$K$251,$B$3,'Raw Data'!$G$2:$G$251,$B$4,'Raw Data'!$J$2:$J$251,$B$5) -> 1909.93 | D91: =RANK(C91,$C$82:$C$131)+COUNTIF($C$82:C91,C91)-1 -> 38
A92: =Analysis!B95 -> William White | B92: =Analysis!A95 -> CUST011 | C92: =SUMIFS('Raw Data'!$N$2:$N$251,'Raw Data'!$C$2:$C$251,B92,'Raw Data'!$K$2:$K$251,$B$3,'Raw Data'!$G$2:$G$251,$B$4,'Raw Data'!$J$2:$J$251,$B$5) -> 4749.91 | D92: =RANK(C92,$C$82:$C$131)+COUNTIF($C$82:C92,C92)-1 -> 23
A93: =Analysis!B96 -> Patricia Moore | B93: =Analysis!A96 -> CUST012 | C93: =SUMIFS('Raw Data'!$N$2:$N$251,'Raw Data'!$C$2:$C$251,B93,'Raw Data'!$K$2:$K$251,$B$3,'Raw Data'!$G$2:$G$251,$B$4,'Raw Data'!$J$2:$J$251,$B$5) -> 9799.73 | D93: =RANK(C93,$C$82:$C$131)+COUNTIF($C$82:C93,C93)-1 -> 4
A94: =Analysis!B97 -> Joseph Jackson | B94: =Analysis!A97 -> CUST013 | C94: =SUMIFS('Raw Data'!$N$2:$N$251,'Raw Data'!$C$2:$C$251,B94,'Raw Data'!$K$2:$K$251,$B$3,'Raw Data'!$G$2:$G$251,$B$4,'Raw Data'!$J$2:$J$251,$B$5) -> 6949.84 | D94: =RANK(C94,$C$82:$C$131)+COUNTIF($C$82:C94,C94)-1 -> 10
A95: =Analysis!B98 -> Linda Martin | B95: =Analysis!A98 -> CUST014 | C95: =SUMIFS('Raw Data'!$N$2:$N$251,'Raw Data'!$C$2:$C$251,B95,'Raw Data'!$K$2:$K$251,$B$3,'Raw Data'!$G$2:$G$251,$B$4,'Raw Data'!$J$2:$J$251,$B$5) -> 1289.9 | D95: =RANK(C95,$C$82:$C$131)+COUNTIF($C$82:C95,C95)-1 -> 43
A96: =Analysis!B99 -> Richard Lee | B96: =Analysis!A99 -> CUST015 | C96: =SUMIFS('Raw Data'!$N$2:$N$251,'Raw Data'!$C$2:$C$251,B96,'Raw Data'!$K$2:$K$251,$B$3,'Raw Data'!$G$2:$G$251,$B$4,'Raw Data'!$J$2:$J$251,$B$5) -> 739.93 | D96: =RANK(C96,$C$82:$C$131)+COUNTIF($C$82:C96,C96)-1 -> 46
A97: =Analysis!B100 -> Elizabeth Hall | B97: =Analysis!A100 -> CUST016 | C97: =SUMIFS('Raw Data'!$N$2:$N$251,'Raw Data'!$C$2:$C$251,B97,'Raw Data'!$K$2:$K$251,$B$3,'Raw Data'!$G$2:$G$251,$B$4,'Raw Data'!$J$2:$J$251,$B$5) -> 3649.86 | D97: =RANK(C97,$C$82:$C$131)+COUNTIF($C$82:C97,C97)-1 -> 31
A98: =Analysis!B101 -> Charles Allen | B98: =Analysis!A101 -> CUST017 | C98: =SUMIFS('Raw Data'!$N$2:$N$251,'Raw Data'!$C$2:$C$251,B98,'Raw Data'!$K$2:$K$251,$B$3,'Raw Data'!$G$2:$G$251,$B$4,'Raw Data'!$J$2:$J$251,$B$5) -> 5089.73 | D98: =RANK(C98,$C$82:$C$131)+COUNTIF($C$82:C98,C98)-1 -> 20
... A131: =Analysis!B134 -> Julie Foster | B131: =Analysis!A134 -> CUST050 | C131: =SUMIFS('Raw Data'!$N$2:$N$251,'Raw Data'!$C$2:$C$251,B131,'Raw Data'!$K$2:$K$251,$B$3,'Raw Data'!$G$2:$G$251,$B$4,'Raw Data'!$J$2:$J$251,$B$5) -> 239.96 | D131: =RANK(C131,$C$82:$C$131)+COUNTIF($C$82:C131,C131)-1 -> 49

Sheet Insights Report
B1: FINAL REPORT - INSIGHTS & STORYTELLING
B2: Every sentence below is a live formula, so it updates when the data changes.
B4: 1. Headline
B5: ="The business earned "&TEXT(Analysis!B39,"$#,##0")&" from "&TEXT(COUNTA('Raw Data'!$A$2:$A$251),"#,##0")&" orders placed by "&COUNTIF(Analysis!E85:E134,">0")&" customers between "&TEXT(Analysis!B6,"mmm yyyy")&" and "&TEXT(Analysis!B7,"mmm yyyy")&". The average order is worth "&TEXT(Analysis!E180,"$#,##0")&"." -> The business earned $229,192 from 250 orders placed by 50 customers between Apr 2024 and Apr 2025. The average order is worth $917.
B7: 2. Regional sales
B8: =Analysis!B181&" is the strongest region with "&TEXT(MAX(Analysis!D175:D179),"0.0%")&" of total revenue ("&TEXT(MAX(Analysis!C175:C179),"$#,##0")&"). The weakest region is "&Analysis!B182&" with "&TEXT(MIN(Analysis!D175:D179),"0.0%")&" - the best place to look for growth." -> East is the strongest region with 25.9% of total revenue ($59,288). The weakest region is South with 15.9% - the best place to look for growth.
B10: 3. Customers
B11: ="Top customer is "&Analysis!B138&" ("&TEXT(Analysis!E138,"0.0%")&" of revenue). The "&Analysis!B143&" High-Value customers (top "&TEXT(Analysis!B80,"0%")&") bring "&TEXT(Analysis!D143,"0%")&" of all revenue, so protecting them matters most." -> Top customer is Mark Carter (6.8% of revenue). The 10 High-Value customers (top 20%) bring 41% of all revenue, so protecting them matters most.
B13: 4. Loyalty
B14: =TEXT(Analysis!D164,"0%")&" of customers bought more than once. The most loyal buyer is "&Analysis!B162&" with "&Analysis!B163&" orders." -> 94% of customers bought more than once. The most loyal buyer is Mark Carter with 12 orders.
B16: 5. Products
B17: ="The most frequently bought product is "&Analysis!B159&"; the most units sold is "&Analysis!B160&"; the highest revenue comes from "&Analysis!B161&". Volume and value can be different stories." -> The most frequently bought product is Bookshelf; the most units sold is Bookshelf; the highest revenue comes from Laptop. Volume and value can be different stories.
B19: 6. Trend & forecast
B20: =Analysis!H61&". The model explains "&TEXT(Analysis!I58,"0%")&" of month-to-month variation (R-squared) and forecasts about "&TEXT(Analysis!I60,"$#,##0")&" for the next month." -> Revenue is trending UP by about $338 every month. The model explains 8% of month-to-month variation (R-squared) and forecasts about $20,330 for the next month.
B22: 7. What-if
B23: ="With price "&TEXT(Analysis!B40,"+0%;-0%")&", quantity "&TEXT(Analysis!B41,"+0%;-0%")&" and discount "&TEXT(Analysis!B42,"0%")&", revenue would be "&TEXT(Analysis!B43,"$#,##0")&" ("&TEXT(Analysis!B44,"+$#,##0;-$#,##0")&" vs actual). Best case "&TEXT(Analysis!E50,"$#,##0")&", worst case "&TEXT(Analysis!E52,"$#,##0")&"." -> With price +5%, quantity +10% and discount 2%, revenue would be $259,423 (+$30,230 vs actual). Best case $289,928, worst case $206,846.
B25: 8. Recommendations (edit after you read the numbers)
B26: Focus retention offers on High-Value and repeat customers; run a campaign in the weakest region; bundle the most-bought product with high-revenue products to lift average order value.

Sheet Manual Steps
A1: STEP-BY-STEP: features that must be done by hand in Excel
A3: PIVOT TABLES | B3: 1) Click any cell in the Raw Data table. 2) Insert > PivotTable > New Worksheet, name it 'Pivots'. 3) Pivot 1: Rows = Region, Values = Sum of Total_Amount. 4) Pivot 2: Rows = Month End (group by Months and Years), Values = Sum of Total_Amount. 5) Pivot 3: Rows = Category, Values = Sum of Total_Amount. 6) Pivot 4: Rows = Product_Name, Values = Sum of Quantity.
A4: PIVOT CHARTS | B4: Click inside a pivot > PivotTable Analyze > PivotChart. Pivot 1 = Bar (clustered column), Pivot 2 = Line, Pivot 3 = Pie. Cut the charts and paste them on the Dashboard sheet (below the existing charts, or replace them).
A5: SLICERS | B5: Click a pivot > PivotTable Analyze > Insert Slicer > tick Region, Category, Payment_Method, Customer_Segment. Right-click each slicer > Report Connections > tick ALL pivots so one click filters the whole dashboard.
A6: TIMELINE | B6: Click a pivot > PivotTable Analyze > Insert Timeline > Date. Connect it to all pivots with Report Connections. Drag the bar to filter by months.
A7: SCENARIO MANAGER | B7: Data > What-If Analysis > Scenario Manager > Add. Changing cells: Analysis!B40:B42. Best = 10%, 15%, 0% | Base = 5%, 10%, 2% | Worst = 0%, -5%, 5%. Then click Summary > Scenario summary, Result cell = Analysis!B43.
A8: GOAL SEEK | B8: Data > What-If Analysis > Goal Seek. Set cell = Analysis!B43 | To value = the number in B45 | By changing cell = Analysis!B40. Excel finds the price increase needed to reach the target revenue.
A9: REGRESSION (Data Analysis Toolpak) | B9: File > Options > Add-ins > Manage Excel Add-ins > Go > tick Analysis ToolPak. Data > Data Analysis > Regression. Input Y Range = Analysis!D56:D66 | Input X Range = Analysis!A56:A66 | tick Labels off | Output = New Worksheet. Read: R Square (how well the line fits), Significance F (below 0.05 means the trend is real), X Variable 1 coefficient (= slope in I56).
A10: ITERATIVE TIMESTAMP | B10: File > Options > Formulas > tick 'Enable iterative calculation'. Then =IF(B34="","",IF(B35="",NOW(),B35)) in B35 freezes the time when B34 is filled.
A11: FILTER (Excel 365) | B11: In a blank area type the formula shown in Analysis!B17. It spills all matching rows automatically. Change Analysis!B16 to switch region.
